atoparser/__init__.py
atoparser/reader.py
atoparser/utils.py
atoparser/parsers/__init__.py
atoparser/parsers/atop_1_26.py
atoparser/structs/__init__.py
atoparser/structs/atop_1_26.py
atoparser/structs/atop_2_10.py
atoparser/structs/atop_2_11.py
atoparser/structs/atop_2_3.py
atoparser/structs/atop_2_4.py
atoparser/structs/atop_2_5.py
atoparser/structs/atop_2_6.py
atoparser/structs/atop_2_7.py
atoparser/structs/atop_2_8.py
atoparser/structs/atop_2_9.py
atoparser/structs/shared.py
atoparser-3.3.0.dist-info/LICENSE
atoparser-3.3.0.dist-info/METADATA
atoparser-3.3.0.dist-info/WHEEL
atoparser-3.3.0.dist-info/entry_points.txt
atoparser-3.3.0.dist-info/top_level.txt
atoparser-3.3.0.dist-info/RECORD
