Metadata-Version: 2.1
Name: atoparser
Version: 3.3.0
Summary: Utilities for reading Atop files natively in Python
Author: David Fritz
License: MIT
Project-URL: Home, https://github.com/pyranha-labs/atoparser
Project-URL: Changelog, https://github.com/pyranha-labs/atoparser/releases
Project-URL: Issues, https://github.com/pyranha-labs/atoparser/issues
Keywords: monitoring,analysis,diagnostics,utilization,atop
Platform: Linux
Classifier: Development Status :: 5 - Production/Stable
Classifier: Intended Audience :: Developers
Classifier: Intended Audience :: Science/Research
Classifier: License :: OSI Approved :: MIT License
Classifier: Programming Language :: Python
Classifier: Programming Language :: Python :: 3
Classifier: Programming Language :: Python :: 3 :: Only
Classifier: Programming Language :: Python :: 3.10
Classifier: Programming Language :: Python :: 3.11
Classifier: Topic :: Software Development
Classifier: Topic :: Scientific/Engineering
Classifier: Typing :: Typed
Classifier: Operating System :: POSIX :: Linux
Requires-Python: >=3.10
License-File: LICENSE
